{
    "actions": {
        "save": {
            "label": "Save",
            "shortcut": "ctrl+s"
        },
        "open": {
            "label": "Open",
            "shortcut": "ctrl+o"
        },
        "closeApp": {
            "label": "Close App",
            "shortcut": "ctrl+w"
        },
        "newFrame": {
            "label": "New Frame",
            "shortcut": "ctrl+f"
        },
        "resetZoom": {
            "label": "Reset Zoom",
            "shortcut": ""
        },
        "focusAll": {
            "label": "Focus All",
            "shortcut": "f"
        },
        "deleteImage": {
            "label": "Delete Image",
            "shortcut": "delete"
        },
        "deleteFrame": {
            "label": "Delete Frame",
            "shortcut": "delete"
        },
        "duplicateImage": {
            "label": "Duplicate Image",
            "shortcut": ""
        },
        "renameFrame": {
            "label": "Rename Frame",
            "shortcut": ""
        }
    },
    "mouse": {
        "dragImage": {
            "label": "Drag / Select",
            "button": 0
        },
        "panView": {
            "label": "Pan View",
            "button": 1
        },
        "menuOpen": {
            "label": "Context Menu",
            "button": 2
        }
    }
}
